tox_virtualenv_no_download.py
tox_virtualenv_no_download-1.1.0.dist-info/LICENSE
tox_virtualenv_no_download-1.1.0.dist-info/METADATA
tox_virtualenv_no_download-1.1.0.dist-info/WHEEL
tox_virtualenv_no_download-1.1.0.dist-info/entry_points.txt
tox_virtualenv_no_download-1.1.0.dist-info/top_level.txt
tox_virtualenv_no_download-1.1.0.dist-info/RECORD
